README.md
setup.cfg
setup.py
pyonlib/__init__.py
pyonlib/errors.py
pyonlib.egg-info/PKG-INFO
pyonlib.egg-info/SOURCES.txt
pyonlib.egg-info/dependency_links.txt
pyonlib.egg-info/requires.txt
pyonlib.egg-info/top_level.txt