Metadata-Version: 2.1
Name: pyonlib
Version: 0.1.33
Summary: 解析pyon文件，即保存一个python词典的文件，和json类似。
Home-page: https://code.xueersi.com
Author: Ruoyu Wang
License: UNKNOWN
Platform: UNKNOWN
